kiwoomOS/__init__.py
kiwoomOS/kwos.py
kiwoomOS-0.93.dist-info/METADATA
kiwoomOS-0.93.dist-info/RECORD
kiwoomOS-0.93.dist-info/WHEEL
kiwoomOS-0.93.dist-info/top_level.txt
