Metadata-Version: 2.1
Name: kiwoomOS
Version: 0.93
Summary: Python wrapper for kiwoom api
Home-page: https://github.com/junyoung-jamong/KiwoomOS
Author: Kang Jun Young
Author-email: msmapark2@gmail.com
License: UNKNOWN
Keywords: 키움OpenAPI,키움API
Platform: UNKNOWN
Classifier: Programming Language :: Python :: 3
Classifier: Programming Language :: Python :: 3.2
Classifier: Programming Language :: Python :: 3.3
Classifier: Programming Language :: Python :: 3.4
Classifier: Programming Language :: Python :: 3.5
Classifier: Programming Language :: Python :: 3.6
Requires-Python: >=3
